{
  "main": {
    "id": "3cfb8af0a1ea3595",
    "type": "split",
    "children": [
      {
        "id": "2f1983149fa33e50",
        "type": "tabs",
        "children": [
          {
            "id": "1680c76b7776577f",
            "type": "leaf",
            "state": {
              "type": "markdown",
              "state": {
                "file": "Wine/Tasting/San Marzano Collezione Cinquanta.md",
                "mode": "preview",
                "source": true
              },
              "icon": "lucide-file",
              "title": "San Marzano Collezione Cinquanta"
            }
          },
          {
            "id": "1e891bebc2bd949b",
            "type": "leaf",
            "state": {
              "type": "split-diff-view",
              "state": {
                "aFile": "conflict-files-obsidian-git.md",
                "bFile": "conflict-files-obsidian-git.md",
                "aRef": ""
              },
              "icon": "diff",
              "title": "Diff: conflict-files-obsidian-git"
            }
          },
          {
            "id": "1d490fca1b697271",
            "type": "leaf",
            "state": {
              "type": "markdown",
              "state": {
                "file": "conflict-files-obsidian-git.md",
                "mode": "source",
                "source": false
              },
              "icon": "lucide-file",
              "title": "conflict-files-obsidian-git"
            }
          }
        ],
        "currentTab": 2
      }
    ],
    "direction": "vertical"
  },
  "left": {
    "id": "973ae542c84c8496",
    "type": "split",
    "children": [
      {
        "id": "b3183e94f44a4aa9",
        "type": "tabs",
        "children": [
          {
            "id": "c7f78908a0a58d68",
            "type": "leaf",
            "state": {
              "type": "file-explorer",
              "state": {
                "sortOrder": "alphabetical",
                "autoReveal": false
              },
              "icon": "lucide-folder-closed",
              "title": "ファイルエクスプローラ"
            }
          },
          {
            "id": "4cdc42e593524c99",
            "type": "leaf",
            "state": {
              "type": "search",
              "state": {
                "query": "tag:#Wine",
                "matchingCase": false,
                "explainSearch": false,
                "collapseAll": false,
                "extraContext": false,
                "sortOrder": "alphabetical"
              },
              "icon": "lucide-search",
              "title": "検索"
            }
          },
          {
            "id": "64580cb6e61441ad",
            "type": "leaf",
            "state": {
              "type": "bookmarks",
              "state": {},
              "icon": "lucide-bookmark",
              "title": "ブックマーク"
            }
          }
        ]
      }
    ],
    "direction": "horizontal",
    "width": 299.5
  },
  "right": {
    "id": "c9627ddc1f068eeb",
    "type": "split",
    "children": [
      {
        "id": "1c7c2afa8903e29a",
        "type": "tabs",
        "children": [
          {
            "id": "95a638d8f28e7fe8",
            "type": "leaf",
            "state": {
              "type": "backlink",
              "state": {
                "file": "conflict-files-obsidian-git.md",
                "collapseAll": false,
                "extraContext": false,
                "sortOrder": "alphabetical",
                "showSearch": false,
                "searchQuery": "",
                "backlinkCollapsed": false,
                "unlinkedCollapsed": true
              },
              "icon": "links-coming-in",
              "title": "conflict-files-obsidian-gitへのバックリンク"
            }
          },
          {
            "id": "e3bd7697d0c2e144",
            "type": "leaf",
            "state": {
              "type": "outgoing-link",
              "state": {
                "file": "conflict-files-obsidian-git.md",
                "linksCollapsed": false,
                "unlinkedCollapsed": true
              },
              "icon": "links-going-out",
              "title": "conflict-files-obsidian-gitからのアウトゴーイングリンク"
            }
          },
          {
            "id": "d6337a1d62cf8beb",
            "type": "leaf",
            "state": {
              "type": "tag",
              "state": {
                "sortOrder": "frequency",
                "useHierarchy": true,
                "showSearch": false,
                "searchQuery": ""
              },
              "icon": "lucide-tags",
              "title": "タグ"
            }
          },
          {
            "id": "7b6302377f56e353",
            "type": "leaf",
            "state": {
              "type": "all-properties",
              "state": {
                "sortOrder": "frequency",
                "showSearch": false,
                "searchQuery": ""
              },
              "icon": "lucide-archive",
              "title": "すべてのプロパティ"
            }
          },
          {
            "id": "4b76f2c65e21aeb9",
            "type": "leaf",
            "state": {
              "type": "outline",
              "state": {
                "file": "conflict-files-obsidian-git.md",
                "followCursor": false,
                "showSearch": false,
                "searchQuery": ""
              },
              "icon": "lucide-list",
              "title": "conflict-files-obsidian-gitのアウトライン"
            }
          },
          {
            "id": "cb4228be23b14fb5",
            "type": "leaf",
            "state": {
              "type": "git-view",
              "state": {},
              "icon": "git-pull-request",
              "title": "Source Control"
            }
          }
        ],
        "currentTab": 5
      }
    ],
    "direction": "horizontal",
    "width": 300
  },
  "left-ribbon": {
    "hiddenItems": {
      "graph:グラフビューを開く": false,
      "switcher:クイックスイッチャーを開く": false,
      "canvas:新規キャンバスを作成": false,
      "daily-notes:今日のデイリーノートを開く": false,
      "templates:テンプレートを挿入": false,
      "command-palette:コマンドパレットを開く": false,
      "bases:Create new base": false,
      "obsidian-git:Open Git source control": false,
      "templater-obsidian:Templater": false
    }
  },
  "active": "1d490fca1b697271",
  "lastOpenFiles": [
    "conflict-files-obsidian-git.md",
    "Wine/Tasting/San Marzano Collezione Cinquanta.md",
    "Wine/Tasting/Untitled.md",
    "Wine/Tasting/Test.md",
    "Templates/Wine_Tasting_Template.md",
    "IMG_8495.jpeg",
    "Wine/Grapes/Cabernet Sauvignon.md",
    "Wine/Tasting",
    "MOC/Wine Grape.md",
    "MOC/Wine Region.md",
    "MOC/Wine.md",
    "Wine/Grapes/Pinot Noir.md",
    "MOC/Wine Grap.md",
    "MOC/Wine Region copy.md",
    "MOC/Wine copy.md",
    "Wine/Regions/France/Bourgogne.md",
    "Wine/Assets/Wine_Pinot_Noir.jpeg",
    "Wine/Assets/Wine_Bourgogne_Rank.jpeg",
    "Wine/Assets/Wine_Bourgogne_Rank.webp",
    "Wine/Regions/Italy/Puglia.md",
    "Wine/Assets/Wine_Region_France_Bourgogne.jpg",
    "Wine/Assets/Wine_Region_France_ Bourgogne.jpg",
    "AGENTS.md",
    "Wine/Regions/Spain",
    "Wine/Regions/Chile",
    "Wine/Regions/USA",
    "Wine/Regions/France/Beaujolais Nouveau（ボジョレー・ヌーボー）.md",
    "Wine/Regions",
    "Templates/Wine_Grape_Template.md",
    "Wine/France/Bordeaux.md",
    "Templates/Wine_Area_Template.md",
    "Wine/Assets/Wine_Cabernet_Sauvignon.jpeg",
    "Wine/Assets/Wine_Cabernet_Sauvignon_Region.jpeg",
    "Templates/Wine_Area_Template copy.md",
    "Wine/Grapes/Semillon.md",
    "Wine/Grapes/Primitivo.md",
    "Wine/Assets/Wine_Region_Italy_Puglia.jpg",
    "Tasting/タンニン.md",
    "Tasting",
    "Templates/Wine.md",
    "Maps.md",
    "Wine/Grapes",
    "Wine/Assets/Wine_Region_Italy.jpg",
    "Templates",
    "MOC",
    "Wine/Regions/Italy",
    "無題のファイル.canvas",
    "Wine/Tasting.canvas"
  ]
}